migrator/__init__.py
migrator/main.py
redis_migrate-1.0.0.dist-info/METADATA
redis_migrate-1.0.0.dist-info/RECORD
redis_migrate-1.0.0.dist-info/WHEEL
redis_migrate-1.0.0.dist-info/entry_points.txt
redis_migrate-1.0.0.dist-info/top_level.txt
