Metadata-Version: 2.1
Name: redis-migrate
Version: 1.0.0
Summary: A simple command line tool for redis data migration
Home-page: https://github.com/mingrammer/redis-migrate
Author: mingrammer
Author-email: mingrammer@gmail.com
License: MIT
Keywords: redis migrate
Platform: UNKNOWN
Classifier: License :: OSI Approved :: MIT License
Classifier: Programming Language :: Python
Classifier: Programming Language :: Python :: 3
Classifier: Programming Language :: Python :: 3.3
Classifier: Programming Language :: Python :: 3.4
Classifier: Programming Language :: Python :: 3.5
Classifier: Programming Language :: Python :: 3.6
Classifier: Programming Language :: Python :: Implementation :: CPython
Classifier: Topic :: Terminals
Requires-Python: >=3
Requires-Dist: click (==6.7)
Requires-Dist: redis (==2.10.6)
Requires-Dist: tqdm (==4.26.0)
